econometrics01/__init__.py
econometrics01-1.0.1.dist-info/METADATA
econometrics01-1.0.1.dist-info/WHEEL
econometrics01-1.0.1.dist-info/top_level.txt
econometrics01-1.0.1.dist-info/RECORD
