Metadata-Version: 2.1
Name: econometrics01
Version: 1.0.1
Summary: This is the simplest modufwle for work with files. v2
Author: fertic
Author-email: foxmine852@gmail.com
Keywords: files speedfiles
Classifier: Programming Language :: Python :: 3.10
Classifier: License :: OSI Approved :: MIT License
Classifier: Operating System :: OS Independent
Requires-Dist: requests >=2.25.1
